jupyterdrive/__init__.py
jupyterdrive/__main__.py
jupyterdrive/clientsidenbmanager.py
jupyterdrive/ipython_notebook_config.json
jupyterdrive/mixed_contents.json
jupyterdrive/mixednbmanager.py
jupyterdrive/gdrive/drive-contents.js
jupyterdrive/gdrive/drive_utils.js
jupyterdrive/gdrive/gapi_utils.js
jupyterdrive/gdrive/mixed-contents.js
jupyterdrive/gdrive/notebook_model.js
jupyterdrive/gdrive/picker_utils.js
jupyterdrive-1.1.0.dist-info/DESCRIPTION.rst
jupyterdrive-1.1.0.dist-info/METADATA
jupyterdrive-1.1.0.dist-info/metadata.json
jupyterdrive-1.1.0.dist-info/RECORD
jupyterdrive-1.1.0.dist-info/top_level.txt
jupyterdrive-1.1.0.dist-info/WHEEL
