Metadata-Version: 2.0
Name: jupyterdrive
Version: 1.1.0
Summary: Integration of IPython/Jupyter with Google drive
Home-page: https://github.com/jupyter/jupyter-drive
Author: Matthias Bussonnier, Kester Tong, Kyle Kelley, Thomas Kluyver, The IPython team
Author-email: ipython-dev@scipy.org
License: BSD
Keywords: ipython jupyter google drive notebook
Platform: UNKNOWN
Classifier: Development Status :: 4 - Beta
Classifier: Intended Audience :: Developers
Classifier: License :: OSI Approved :: BSD License
Classifier: Programming Language :: Python :: 2
Classifier: Programming Language :: Python :: 2.7
Classifier: Programming Language :: Python :: 3
Classifier: Programming Language :: Python :: 3.3
Classifier: Programming Language :: Python :: 3.4
Classifier: Framework :: IPython
Requires-Dist: IPython
